lovely_pytest_docker-0.1.0-py3.7-nspkg.pth
lovely/pytest/__init__.py
lovely/pytest/docker/__init__.py
lovely/pytest/docker/compose.py
lovely_pytest_docker-0.1.0.dist-info/LICENSE.txt
lovely_pytest_docker-0.1.0.dist-info/METADATA
lovely_pytest_docker-0.1.0.dist-info/WHEEL
lovely_pytest_docker-0.1.0.dist-info/entry_points.txt
lovely_pytest_docker-0.1.0.dist-info/namespace_packages.txt
lovely_pytest_docker-0.1.0.dist-info/top_level.txt
lovely_pytest_docker-0.1.0.dist-info/RECORD
