Metadata-Version: 2.1
Name: lovely-pytest-docker
Version: 0.1.0
Summary: Pytest testing utilities with docker containers.
Home-page: https://github.com/lovelysystems/lovely-pytest-docker
Author: Lovely Systems
Author-email: office@lovelysystems.com
License: UNKNOWN
Keywords: pytest testing docker compose
Platform: UNKNOWN
Classifier: Programming Language :: Python :: 3
Classifier: Programming Language :: Python :: 2.7
Requires-Dist: pytest
